fissix_py35-19.3.dist-info/dependency_links.txt
fissix_py35-19.3.dist-info/entry_points.txt
fissix_py35-19.3.dist-info/METADATA
fissix_py35-19.3.dist-info/top_level.txt
fissix_py35-19.3.dist-info/WHEEL
fissix/pytree.py
fissix/btm_matcher.py
fissix/fixer_util.py
fissix/pygram.py
fissix/patcomp.py
fissix/__main__.py
fissix/btm_utils.py
fissix/__init__.py
fissix/main.py
fissix/refactor.py
fissix/fixer_base.py
fissix/pgen2/grammar.py
fissix/pgen2/literals.py
fissix/pgen2/conv.py
fissix/pgen2/__init__.py
fissix/pgen2/driver.py
fissix/pgen2/pgen.py
fissix/pgen2/parse.py
fissix/pgen2/tokenize.py
fissix/pgen2/token.py
fissix/tests/pytree_idempotency.py
fissix/tests/test_refactor.py
fissix/tests/test_util.py
fissix/tests/test_all_fixers.py
fissix/tests/test_parser.py
fissix/tests/test_pytree.py
fissix/tests/__main__.py
fissix/tests/support.py
fissix/tests/__init__.py
fissix/tests/test_fixers.py
fissix/tests/test_main.py
fissix/tests/data/fixers/myfixes/__init__.py
fissix/tests/data/fixers/myfixes/fix_first.py
fissix/tests/data/fixers/myfixes/fix_preorder.py
fissix/tests/data/fixers/myfixes/fix_explicit.py
fissix/tests/data/fixers/myfixes/fix_last.py
fissix/tests/data/fixers/myfixes/fix_parrot.py
fissix/fixes/fix_apply.py
fissix/fixes/fix_xrange.py
fissix/fixes/fix_map.py
fissix/fixes/fix_getcwdu.py
fissix/fixes/fix_nonzero.py
fissix/fixes/fix_imports.py
fissix/fixes/fix_import.py
fissix/fixes/fix_input.py
fissix/fixes/fix_except.py
fissix/fixes/fix_filter.py
fissix/fixes/fix_sys_exc.py
fissix/fixes/fix_basestring.py
fissix/fixes/fix_itertools.py
fissix/fixes/fix_urllib.py
fissix/fixes/fix_reduce.py
fissix/fixes/fix_raw_input.py
fissix/fixes/fix_exec.py
fissix/fixes/fix_asserts.py
fissix/fixes/fix_renames.py
fissix/fixes/fix_repr.py
fissix/fixes/fix_imports2.py
fissix/fixes/fix_ws_comma.py
fissix/fixes/fix_isinstance.py
fissix/fixes/fix_reload.py
fissix/fixes/__init__.py
fissix/fixes/fix_funcattrs.py
fissix/fixes/fix_standarderror.py
fissix/fixes/fix_execfile.py
fissix/fixes/fix_unicode.py
fissix/fixes/fix_itertools_imports.py
fissix/fixes/fix_intern.py
fissix/fixes/fix_metaclass.py
fissix/fixes/fix_exitfunc.py
fissix/fixes/fix_raise.py
fissix/fixes/fix_idioms.py
fissix_py35-19.3.dist-info/LICENSE
fissix_py35-19.3.dist-info/RECORD