Metadata-Version: 2.1
Name: fissix-py35
Version: 19.3
Summary: Backport of lib2to3, with enhancements
Project-URL: Home, https://github.com/orsinium/fissix-py35
Author: John Reese
Author-email: john@noswap.com
License: PSF
Requires-Dist: appdirs
